Sidecord/__init__.py
Sidecord/blacklist.py
Sidecord/bot.py
Sidecord/components.py
Sidecord/emb.py
Sidecord/enums.py
Sidecord/errors.py
Sidecord/logs.py
Sidecord/sql.py
Sidecord/times.py
Sidecord/utils.py
Sidecord/cogs/blacklist.py
Sidecord/cogs/help.py
Sidecord/cogs/status_changer.py
Sidecord/cogs/dpy/blacklist_setup.py
Sidecord/cogs/dpy/help_setup.py
Sidecord/cogs/dpy/status_changer_setup.py
Sidecord/cogs/pyc/blacklist_setup.py
Sidecord/cogs/pyc/help_setup.py
Sidecord/cogs/pyc/status_changer_setup.py
Sidecord/internal/__init__.py
Sidecord/internal/colors.py
Sidecord/internal/config.py
Sidecord/internal/embed_templates.py
Sidecord/internal/ready_style.py
Sidecord/internal/translation.py
Sidecord/internal/dc/__init__.py
Sidecord/internal/dc/dc_imports.py
Sidecord/internal/language/de.json
Sidecord/internal/language/en.json
Sidecord/internal/language/languages.py
Sidecord-0.5.4.dist-info/LICENSE
Sidecord-0.5.4.dist-info/METADATA
Sidecord-0.5.4.dist-info/WHEEL
Sidecord-0.5.4.dist-info/top_level.txt
Sidecord-0.5.4.dist-info/RECORD
